munchqin/__init__.py
munchqin-0.0.0.dist-info/METADATA
munchqin-0.0.0.dist-info/WHEEL
munchqin-0.0.0.dist-info/top_level.txt
munchqin-0.0.0.dist-info/RECORD
