Metadata-Version: 2.1
Name: munchqin
Version: 0.0.0
Summary: Impending.
Author-email: John Dumbell <euphoriceulogy@gmail.com>
